supersekrit/__init__.py
supersekrit-0.1.0.dist-info/WHEEL
supersekrit-0.1.0.dist-info/METADATA
supersekrit-0.1.0.dist-info/RECORD
